Workbook

Sheet START HERE
A1: BOYNT — Year 1 Financial Tracker
A2: Floating sunglasses, funded by you and your backers. This page explains how the whole workbook fits together.
A5: HOW THE WORKBOOK IS ORGANIZED
B7: Money coming IN is tracked on two tabs:
B8: Funding | C8: Every dollar you raise before/while starting up: Kickstarter pledges, donations, your own money, loans.
B9: Sales Log | C9: Every dollar customers pay you for sunglasses. One row per product per order.
B11: Money going OUT is tracked on two tabs:
B12: Capital | C12: One-time startup equipment: 3D printer, injection molder, tools, LLC filing. Things you buy ONCE.
B13: Operating Costs | C13: Everything you keep paying for: materials, packaging, insurance, website, marketing, fees.
B15: Reference & planning tabs:
B16: Products & Pricing | C16: Your official price list. Every dropdown in the workbook pulls from this tab.
B17: COGS | C17: What ONE pair of each model costs you to make. Auto-calculates your true profit per pair.
B18: Orders | C18: Who ordered what, where it ships, and whether you have fulfilled it yet.
B20: Summary tabs (all-formula, you never type on these):
B21: Dashboard | C21: The big picture: total in, total out, cash position, profit, order stats. Green = healthy, red = in the hole.
B22: Monthly Cash Flow | C22: Month-by-month money in vs. out with a running cash balance.
A24: COLOR KEY (used on every tab)
B26: Instructions | C26: Instruction blocks — read these, never type over them.
B27: Headers | C27: Column headers.
B28: Auto-calculated | C28: Calculated cells — formulas live here. Don't type in them; they fill in automatically.
B29: Your input | C29: Input cells — this is where YOU type.
B30: Positive | C30: Automatic: shown when money in ≥ money out (you're ahead).
B31: Negative | C31: Automatic: shown when money out > money in (you're in the hole).
A33: YOUR WEEKLY ROUTINE (10 minutes)
B35: 1. | C35: New pledge or donation came in? → Add a row on Funding.
B36: 2. | C36: Made a sale? → Add a row on Sales Log AND a row on Orders (same Order #).
B37: 3. | C37: Shipped something? → On Orders, fill Date Shipped + Tracking #, set Status, flip Fulfilled? to Yes.
B38: 4. | C38: Bought anything? → Equipment goes on Capital; everything else goes on Operating Costs.
B39: 5. | C39: Glance at Dashboard and Monthly Cash Flow. If numbers are red, you're spending faster than you're earning.
A41: TIPS
B43: • | C43: Kickstarter keeps ~5% + ~3-5% payment processing. Enter the FEE in the Fees column on Funding so your net is accurate.
B44: • | C44: Always use the product names from Products & Pricing (the dropdowns do this for you) — the formulas match on exact names.
B45: • | C45: Enter dates on everything. The Monthly Cash Flow tab sorts your money into months using those dates.
B46: • | C46: Save a copy before big edits. If a blue formula cell gets deleted, copy it down from the row above.

Sheet Dashboard
A1: Dashboard — BOYNT Year 1 at a Glance
A2: All-formula summary. Green means you're ahead; red means you're in the hole. Never type on this tab.
A4: WHAT THIS TAB IS FOR: the 30-second health check. Every number pulls live from the other tabs the moment you
A5: log something. CASH VIEW = actual dollars in vs. out (includes funding & equipment). PROFIT VIEW = is the
A6: business itself making money on the glasses it sells (sales minus what they cost to make and run)?
B8: CASH VIEW — money in vs. money out | E8: PROFIT VIEW — is the business itself profitable?
B9: Funding raised (net of fees) | C9: =Funding!$G$314 | E9: Sales revenue (net) | F9: ='Sales Log'!$L$314
B10: Sales revenue (net) | C10: ='Sales Log'!$L$314 | E10: Cost of goods sold (per-pair × units) | F10: =COGS!$I$29
B11: TOTAL MONEY IN | C11: =C9+C10 | E11: GROSS PROFIT | F11: =F9-F10
B13: Capital equipment spent | C13: =SUMIFS(Capital!$G$14:$G$63,Capital!$E$14:$E$63,">0") | E13: Operating costs (excl. materials)* | F13: ='Operating Costs'!$E$213-SUMIFS('Operating Costs'!$E$13:$E$212,'Operating Costs'!$C$13:$C$212,"Materials & Product Supplies")
B14: Operating costs paid | C14: ='Operating Costs'!$E$213 | E14: EST. NET PROFIT | F14: =F11-F13
B15: TOTAL MONEY OUT | C15: =C13+C14 | E15: Profit margin | F15: =IF(N(F9)=0,"",F14/F9)
E16: *Materials are excluded here because they're already
B17: CASH POSITION (In − Out) | C17: =C11-C15 | E17: counted per-pair inside COGS — no double counting.
B18: Green = you have more than you've spent. Red = you're in debt.
B20: ORDERS & FULFILLMENT | E20: FUNDING BREAKDOWN
B21: Orders received | C21: =Orders!$C$13 | E21: Kickstarter raised (net) | F21: =Funding!D11
B22: Orders fulfilled | C22: =Orders!$E$13 | E22: Donations | F22: =SUMIFS(Funding!$G$14:$G$313,Funding!$B$14:$B$313,"Donation")
B23: Orders still open | C23: =Orders!$H$13 | E23: Kickstarter goal | F23: =Funding!B11
B24: Pairs sold (units) | C24: ='Sales Log'!$E$314 | E24: % of goal reached | F24: =IF(N(F23)=0,"",F21/F23)

Sheet Products & Pricing
A1: Products & Pricing — Official Price List
A2: The master list of everything BOYNT sells. Every product dropdown in this workbook pulls from column A.
A4: WHAT THIS TAB IS FOR: one row per product you sell. It feeds the dropdowns on Sales Log, Orders, and COGS,
A5: and it shows your profit per pair once COGS is filled in.
A6: WHAT GOES HERE: Product Name (exact name you sell under), Frame Style, Lens/Colorway, and your Selling Price.
A7: Cost per Unit, Profit, and Margin % are AUTOMATIC — they come from the COGS tab. Don't type in the blue columns.
A8: WHEN TO UPDATE: add a row when you launch a new model or colorway; edit the price if you change pricing.
A9: NOTE: your 9 launch products and prices are pre-loaded from your class spreadsheet — edit them freely.
A13: Product Name | B13: Frame Style | C13: Lens / Colorway | D13: Selling Price | E13: Cost per Unit (auto from COGS) | F13: Profit per Pair (auto) | G13: Margin % (auto)
A14: The Classics | B14: The Classics | C14: Grey Lens | D14: 25 | E14: =IF(A14="","",COGS!G14) | F14: =IF(OR(A14="",E14=""),"",D14-E14) | G14: =IF(OR(A14="",E14="",D14=0),"",(D14-E14)/D14)
A15: The Classics Ocean Blue | B15: The Classics | C15: Blue Mirror REVO | D15: 28 | E15: =IF(A15="","",COGS!G15) | F15: =IF(OR(A15="",E15=""),"",D15-E15) | G15: =IF(OR(A15="",E15="",D15=0),"",(D15-E15)/D15)
A16: The Classics Driftwood Sand | B16: The Classics | C16: Brown / Amber | D16: 30 | E16: =IF(A16="","",COGS!G16) | F16: =IF(OR(A16="",E16=""),"",D16-E16) | G16: =IF(OR(A16="",E16="",D16=0),"",(D16-E16)/D16)
A17: Drifters | B17: Drifters | C17: Grey | D17: 30 | E17: =IF(A17="","",COGS!G17) | F17: =IF(OR(A17="",E17=""),"",D17-E17) | G17: =IF(OR(A17="",E17="",D17=0),"",(D17-E17)/D17)
A18: Drifters Seafoam | B18: Drifters | C18: Light Green / Grey | D18: 32 | E18: =IF(A18="","",COGS!G18) | F18: =IF(OR(A18="",E18=""),"",D18-E18) | G18: =IF(OR(A18="",E18="",D18=0),"",(D18-E18)/D18)
A19: Drifters Storm Grey | B19: Drifters | C19: Grey | D19: 35 | E19: =IF(A19="","",COGS!G19) | F19: =IF(OR(A19="",E19=""),"",D19-E19) | G19: =IF(OR(A19="",E19="",D19=0),"",(D19-E19)/D19)
A20: The Currents | B20: The Currents | C20: Grey | D20: 35 | E20: =IF(A20="","",COGS!G20) | F20: =IF(OR(A20="",E20=""),"",D20-E20) | G20: =IF(OR(A20="",E20="",D20=0),"",(D20-E20)/D20)
A21: The Currents Deep Ocean | B21: The Currents | C21: Blue Mirror REVO | D21: 38 | E21: =IF(A21="","",COGS!G21) | F21: =IF(OR(A21="",E21=""),"",D21-E21) | G21: =IF(OR(A21="",E21="",D21=0),"",(D21-E21)/D21)
A22: The Currents Driftwood Sand | B22: The Currents | C22: Brown / Amber | D22: 40 | E22: =IF(A22="","",COGS!G22) | F22: =IF(OR(A22="",E22=""),"",D22-E22) | G22: =IF(OR(A22="",E22="",D22=0),"",(D22-E22)/D22)
E23: =IF(A23="","",COGS!G23) | F23: =IF(OR(A23="",E23=""),"",D23-E23) | G23: =IF(OR(A23="",E23="",D23=0),"",(D23-E23)/D23)
E24: =IF(A24="","",COGS!G24) | F24: =IF(OR(A24="",E24=""),"",D24-E24) | G24: =IF(OR(A24="",E24="",D24=0),"",(D24-E24)/D24)
E25: =IF(A25="","",COGS!G25) | F25: =IF(OR(A25="",E25=""),"",D25-E25) | G25: =IF(OR(A25="",E25="",D25=0),"",(D25-E25)/D25)
E26: =IF(A26="","",COGS!G26) | F26: =IF(OR(A26="",E26=""),"",D26-E26) | G26: =IF(OR(A26="",E26="",D26=0),"",(D26-E26)/D26)
E27: =IF(A27="","",COGS!G27) | F27: =IF(OR(A27="",E27=""),"",D27-E27) | G27: =IF(OR(A27="",E27="",D27=0),"",(D27-E27)/D27)
E28: =IF(A28="","",COGS!G28) | F28: =IF(OR(A28="",E28=""),"",D28-E28) | G28: =IF(OR(A28="",E28="",D28=0),"",(D28-E28)/D28)

Sheet COGS
A1: COGS — Cost of Goods Sold (what ONE pair costs you to make)
A2: Break down the cost of producing a single pair of each model. This is where you find out your real profit.
A4: WHAT THIS TAB IS FOR: calculating your cost PER PAIR for each model, and your total production cost for the year.
A5: WHAT GOES HERE: in each white column, enter what ONE pair uses: Frame Material (polypropylene/resin), Lenses,
A6: Hinges & Screws, Packaging (box, pouch, cloth), and Other (stickers, cards, thread...).
A7: HOW TO GET PER-PAIR NUMBERS: divide what you paid by how many pairs it covers. Example: $1,400 of screws that
A8: covers 2,500 pairs = $0.56 per pair. A $3,300 packaging kit for 2,000 orders = $1.65 per pair.
A9: WHAT DOES NOT GO HERE: equipment (that's Capital) and general bills like insurance or your website (Operating Costs).
A10: AUTOMATIC: Product names sync from Products & Pricing. Units Sold counts your Sales Log. Total COGS = cost × units.
A11: NOTE: when you BUY materials, also log the purchase on Operating Costs (category: Materials & Product Supplies)
A12: so your cash tracking stays accurate. This tab is the per-unit math; that tab is the actual money leaving your pocket.
A13: Product (auto) | B13: Frame Material $ /pair | C13: Lenses $ /pair | D13: Hinges & Screws $ /pair | E13: Packaging $ /pair | F13: Other $ /pair | G13: TOTAL COST PER PAIR (auto) | H13: Units Sold (auto from Sales Log) | I13: Total COGS (auto)
A14: ='Products & Pricing'!A14&"" | G14: =IF(A14="","",N(B14)+N(C14)+N(D14)+N(E14)+N(F14)) | H14: =IF(A14="","",SUMIFS('Sales Log'!$E$14:$E$313,'Sales Log'!$D$14:$D$313,A14)) | I14: =IF(A14="","",N(G14)*N(H14))
A15: ='Products & Pricing'!A15&"" | G15: =IF(A15="","",N(B15)+N(C15)+N(D15)+N(E15)+N(F15)) | H15: =IF(A15="","",SUMIFS('Sales Log'!$E$14:$E$313,'Sales Log'!$D$14:$D$313,A15)) | I15: =IF(A15="","",N(G15)*N(H15))
A16: ='Products & Pricing'!A16&"" | G16: =IF(A16="","",N(B16)+N(C16)+N(D16)+N(E16)+N(F16)) | H16: =IF(A16="","",SUMIFS('Sales Log'!$E$14:$E$313,'Sales Log'!$D$14:$D$313,A16)) | I16: =IF(A16="","",N(G16)*N(H16))
A17: ='Products & Pricing'!A17&"" | G17: =IF(A17="","",N(B17)+N(C17)+N(D17)+N(E17)+N(F17)) | H17: =IF(A17="","",SUMIFS('Sales Log'!$E$14:$E$313,'Sales Log'!$D$14:$D$313,A17)) | I17: =IF(A17="","",N(G17)*N(H17))
A18: ='Products & Pricing'!A18&"" | G18: =IF(A18="","",N(B18)+N(C18)+N(D18)+N(E18)+N(F18)) | H18: =IF(A18="","",SUMIFS('Sales Log'!$E$14:$E$313,'Sales Log'!$D$14:$D$313,A18)) | I18: =IF(A18="","",N(G18)*N(H18))
A19: ='Products & Pricing'!A19&"" | G19: =IF(A19="","",N(B19)+N(C19)+N(D19)+N(E19)+N(F19)) | H19: =IF(A19="","",SUMIFS('Sales Log'!$E$14:$E$313,'Sales Log'!$D$14:$D$313,A19)) | I19: =IF(A19="","",N(G19)*N(H19))
A20: ='Products & Pricing'!A20&"" | G20: =IF(A20="","",N(B20)+N(C20)+N(D20)+N(E20)+N(F20)) | H20: =IF(A20="","",SUMIFS('Sales Log'!$E$14:$E$313,'Sales Log'!$D$14:$D$313,A20)) | I20: =IF(A20="","",N(G20)*N(H20))
A21: ='Products & Pricing'!A21&"" | G21: =IF(A21="","",N(B21)+N(C21)+N(D21)+N(E21)+N(F21)) | H21: =IF(A21="","",SUMIFS('Sales Log'!$E$14:$E$313,'Sales Log'!$D$14:$D$313,A21)) | I21: =IF(A21="","",N(G21)*N(H21))
A22: ='Products & Pricing'!A22&"" | G22: =IF(A22="","",N(B22)+N(C22)+N(D22)+N(E22)+N(F22)) | H22: =IF(A22="","",SUMIFS('Sales Log'!$E$14:$E$313,'Sales Log'!$D$14:$D$313,A22)) | I22: =IF(A22="","",N(G22)*N(H22))
A23: ='Products & Pricing'!A23&"" | G23: =IF(A23="","",N(B23)+N(C23)+N(D23)+N(E23)+N(F23)) | H23: =IF(A23="","",SUMIFS('Sales Log'!$E$14:$E$313,'Sales Log'!$D$14:$D$313,A23)) | I23: =IF(A23="","",N(G23)*N(H23))
A24: ='Products & Pricing'!A24&"" | G24: =IF(A24="","",N(B24)+N(C24)+N(D24)+N(E24)+N(F24)) | H24: =IF(A24="","",SUMIFS('Sales Log'!$E$14:$E$313,'Sales Log'!$D$14:$D$313,A24)) | I24: =IF(A24="","",N(G24)*N(H24))
A25: ='Products & Pricing'!A25&"" | G25: =IF(A25="","",N(B25)+N(C25)+N(D25)+N(E25)+N(F25)) | H25: =IF(A25="","",SUMIFS('Sales Log'!$E$14:$E$313,'Sales Log'!$D$14:$D$313,A25)) | I25: =IF(A25="","",N(G25)*N(H25))
... A28: ='Products & Pricing'!A28&"" | G28: =IF(A28="","",N(B28)+N(C28)+N(D28)+N(E28)+N(F28)) | H28: =IF(A28="","",SUMIFS('Sales Log'!$E$14:$E$313,'Sales Log'!$D$14:$D$313,A28)) | I28: =IF(A28="","",N(G28)*N(H28))
A29: TOTAL | H29: =SUM(H14:H28) | I29: =SUM(I14:I28)

Sheet Capital
A1: Capital — One-Time Startup Equipment
A2: Big things you buy ONCE to get BOYNT running: printers, molding machines, tools, legal filings.
A4: WHAT THIS TAB IS FOR: tracking every one-time startup purchase and how much of your capital budget is spent.
A5: WHAT GOES HERE: equipment and setup items — 3D printer, injection molding machine, tools, LLC filing, trademarks,
A6: computers, shelving. If you'll buy it once and use it for years, it belongs here.
A7: WHAT DOES NOT GO HERE: materials that go INTO the product (COGS tab / Operating Costs) or recurring bills (Operating Costs).
A8: HOW TO USE IT: one row per item. Paste the vendor link so you can reorder. Set Status: Planned = still shopping,
A9: Ordered = money committed, Received = it's in your hands. Only enter Date Purchased when money actually leaves your
A10: account — that's what tells the Dashboard and Monthly Cash Flow the money is really spent.
B12: Total planned (not yet bought): | C12: =SUMIFS(G14:G63,F14:F63,"Planned") | E12: Total spent (dated rows): | F12: =SUMIFS(G14:G63,E14:E63,">0")
A13: # | B13: Item | C13: Category | D13: Vendor / Link | E13: Date Purchased | F13: Status | G13: Cost | H13: Notes
A14: =IF(B14="","",ROW()-13)
A15: =IF(B15="","",ROW()-13)
A16: =IF(B16="","",ROW()-13)
A17: =IF(B17="","",ROW()-13)
A18: =IF(B18="","",ROW()-13)
A19: =IF(B19="","",ROW()-13)
A20: =IF(B20="","",ROW()-13)
A21: =IF(B21="","",ROW()-13)
A22: =IF(B22="","",ROW()-13)
A23: =IF(B23="","",ROW()-13)
A24: =IF(B24="","",ROW()-13)
A25: =IF(B25="","",ROW()-13)
... A63: =IF(B63="","",ROW()-13)
B64: TOTAL (all rows) | G64: =SUM(G14:G63)

Sheet Operating Costs
A1: Operating Costs — Everything You Keep Paying For
A2: The running costs of doing business: materials, packaging, shipping, insurance, marketing, website, fees.
A4: WHAT THIS TAB IS FOR: logging every expense that is NOT one-time equipment. This is your day-to-day spending record.
A5: WHAT GOES HERE (one row per purchase, on the date you pay):
A6: • Materials & Product Supplies — resin, polypropylene, lenses, screws (also enter per-pair math on the COGS tab)
A7: • Packaging, Shipping & Postage, Insurance, Marketing & Ads, Website & Software subscriptions, Business Fees & Licenses
A8: WHAT DOES NOT GO HERE: one-time equipment (Capital tab).
A9: HOW TO USE IT: pick a Category from the dropdown — the Spending by Category box (right) totals itself and shows
A10: where your money actually goes. The DATE matters: Monthly Cash Flow uses it to place spending in the right month.
A12: Date Paid | B12: Expense | C12: Category | D12: Vendor / Link | E12: Amount | F12: Paid With | G12: Notes | I12: SPENDING BY CATEGORY (auto)
I13: Materials & Product Supplies | J13: =SUMIFS($E$13:$E$212,$C$13:$C$212,"Materials & Product Supplies")
I14: Packaging | J14: =SUMIFS($E$13:$E$212,$C$13:$C$212,"Packaging")
I15: Shipping & Postage | J15: =SUMIFS($E$13:$E$212,$C$13:$C$212,"Shipping & Postage")
I16: Insurance | J16: =SUMIFS($E$13:$E$212,$C$13:$C$212,"Insurance")
I17: Marketing & Ads | J17: =SUMIFS($E$13:$E$212,$C$13:$C$212,"Marketing & Ads")
I18: Website & Software | J18: =SUMIFS($E$13:$E$212,$C$13:$C$212,"Website & Software")
I19: Business Fees & Licenses | J19: =SUMIFS($E$13:$E$212,$C$13:$C$212,"Business Fees & Licenses")
I20: Equipment Repairs | J20: =SUMIFS($E$13:$E$212,$C$13:$C$212,"Equipment Repairs")
I21: Travel | J21: =SUMIFS($E$13:$E$212,$C$13:$C$212,"Travel")
I22: Other | J22: =SUMIFS($E$13:$E$212,$C$13:$C$212,"Other")
B213: TOTAL OPERATING COSTS | E213: =SUM(E13:E212)

Sheet Funding
A1: Funding — Kickstarter, Donations & Startup Money
A2: Every dollar you raise to get BOYNT off the ground, and how close you are to your Kickstarter goal.
A4: WHAT THIS TAB IS FOR: tracking startup money you RAISE (not money you earn from regular sales — that's the Sales Log).
A5: WHAT GOES HERE (one row per pledge/donation): the date, the Type (dropdown), who it came from, what reward tier
A6: they picked (for Kickstarter), the Gross Amount pledged, and any platform Fees. Net Amount calculates itself.
A7: FEES: Kickstarter keeps ~5% plus ~3-5% payment processing. Enter the actual fee so your Net is what really hits your bank.
A8: RECEIVED?: Kickstarter only pays out if the campaign succeeds, and donations can be promised before they arrive —
A9: set Yes only once the money is actually yours. Set your Kickstarter Goal below and watch % of Goal climb.
A11: Kickstarter Goal: | B11: 5000 | C11: Raised toward goal (KS net): | D11: =SUMIFS(G14:G313,B14:B313,"Kickstarter Pledge") | E11: % of Goal: | F11: =IF($B$11=0,"",$D$11/$B$11)
A13: Date | B13: Type | C13: From (Backer / Donor) | D13: Description / Reward Tier | E13: Gross Amount | F13: Fees | G13: Net Amount (auto) | H13: Received? | I13: Notes
G14: =IF(E14="","",E14-N(F14))
G15: =IF(E15="","",E15-N(F15))
G16: =IF(E16="","",E16-N(F16))
G17: =IF(E17="","",E17-N(F17))
G18: =IF(E18="","",E18-N(F18))
G19: =IF(E19="","",E19-N(F19))
G20: =IF(E20="","",E20-N(F20))
G21: =IF(E21="","",E21-N(F21))
G22: =IF(E22="","",E22-N(F22))
G23: =IF(E23="","",E23-N(F23))
G24: =IF(E24="","",E24-N(F24))
G25: =IF(E25="","",E25-N(F25))
... G313: =IF(E313="","",E313-N(F313))
B314: TOTAL RAISED | E314: =SUM(E14:E313) | F314: =SUM(F14:F313) | G314: =SUM(G14:G313)

Sheet Sales Log
A1: Sales Log — Revenue from Every Sale
A2: One row per product per order. This is the money BOYNT earns — the Dashboard and COGS tabs read from here.
A4: WHAT THIS TAB IS FOR: recording the money side of every sale. (The shipping/fulfillment side lives on the Orders tab.)
A5: WHAT GOES HERE: Date, an Order # you make up (0001, 0002...), the Channel it sold through, the Product (dropdown),
A6: and Qty. Unit Price fills in from your price list automatically — type over it if you gave a special price.
A7: Then add Shipping Collected, any Discount, and Processing Fees (Stripe/PayPal/Kickstarter take ~3-5%).
A8: MULTI-ITEM ORDERS: one row PER PRODUCT, repeating the same Order #.
A9: KICKSTARTER REWARDS: when you ship a backer their pair, log it here as Channel = Kickstarter with price $0 if the
A10: pledge was already counted on the Funding tab — otherwise you'd count the same money twice.
A11: AUTOMATIC (blue): Product Total, Order Total, and NET REVENUE calculate themselves. Every sale should also get
A12: a matching row on the Orders tab (same Order #) so you can track fulfillment.
A13: Date | B13: Order # | C13: Channel | D13: Product | E13: Qty | F13: Unit Price (auto) | G13: Product Total (auto) | H13: Shipping Collected | I13: Discount | J13: Order Total (auto) | K13: Processing Fees | L13: NET REVENUE (auto)
F14: =IF($D14="","",IFERROR(VLOOKUP($D14,'Products & Pricing'!$A$14:$D$28,4,FALSE),"")) | G14: =IF($D14="","",N(E14)*N(F14)) | J14: =IF($D14="","",N(G14)+N(H14)-N(I14)) | L14: =IF($D14="","",N(J14)-N(K14))
F15: =IF($D15="","",IFERROR(VLOOKUP($D15,'Products & Pricing'!$A$14:$D$28,4,FALSE),"")) | G15: =IF($D15="","",N(E15)*N(F15)) | J15: =IF($D15="","",N(G15)+N(H15)-N(I15)) | L15: =IF($D15="","",N(J15)-N(K15))
F16: =IF($D16="","",IFERROR(VLOOKUP($D16,'Products & Pricing'!$A$14:$D$28,4,FALSE),"")) | G16: =IF($D16="","",N(E16)*N(F16)) | J16: =IF($D16="","",N(G16)+N(H16)-N(I16)) | L16: =IF($D16="","",N(J16)-N(K16))
F17: =IF($D17="","",IFERROR(VLOOKUP($D17,'Products & Pricing'!$A$14:$D$28,4,FALSE),"")) | G17: =IF($D17="","",N(E17)*N(F17)) | J17: =IF($D17="","",N(G17)+N(H17)-N(I17)) | L17: =IF($D17="","",N(J17)-N(K17))
F18: =IF($D18="","",IFERROR(VLOOKUP($D18,'Products & Pricing'!$A$14:$D$28,4,FALSE),"")) | G18: =IF($D18="","",N(E18)*N(F18)) | J18: =IF($D18="","",N(G18)+N(H18)-N(I18)) | L18: =IF($D18="","",N(J18)-N(K18))
F19: =IF($D19="","",IFERROR(VLOOKUP($D19,'Products & Pricing'!$A$14:$D$28,4,FALSE),"")) | G19: =IF($D19="","",N(E19)*N(F19)) | J19: =IF($D19="","",N(G19)+N(H19)-N(I19)) | L19: =IF($D19="","",N(J19)-N(K19))
F20: =IF($D20="","",IFERROR(VLOOKUP($D20,'Products & Pricing'!$A$14:$D$28,4,FALSE),"")) | G20: =IF($D20="","",N(E20)*N(F20)) | J20: =IF($D20="","",N(G20)+N(H20)-N(I20)) | L20: =IF($D20="","",N(J20)-N(K20))
F21: =IF($D21="","",IFERROR(VLOOKUP($D21,'Products & Pricing'!$A$14:$D$28,4,FALSE),"")) | G21: =IF($D21="","",N(E21)*N(F21)) | J21: =IF($D21="","",N(G21)+N(H21)-N(I21)) | L21: =IF($D21="","",N(J21)-N(K21))
F22: =IF($D22="","",IFERROR(VLOOKUP($D22,'Products & Pricing'!$A$14:$D$28,4,FALSE),"")) | G22: =IF($D22="","",N(E22)*N(F22)) | J22: =IF($D22="","",N(G22)+N(H22)-N(I22)) | L22: =IF($D22="","",N(J22)-N(K22))
F23: =IF($D23="","",IFERROR(VLOOKUP($D23,'Products & Pricing'!$A$14:$D$28,4,FALSE),"")) | G23: =IF($D23="","",N(E23)*N(F23)) | J23: =IF($D23="","",N(G23)+N(H23)-N(I23)) | L23: =IF($D23="","",N(J23)-N(K23))
F24: =IF($D24="","",IFERROR(VLOOKUP($D24,'Products & Pricing'!$A$14:$D$28,4,FALSE),"")) | G24: =IF($D24="","",N(E24)*N(F24)) | J24: =IF($D24="","",N(G24)+N(H24)-N(I24)) | L24: =IF($D24="","",N(J24)-N(K24))
F25: =IF($D25="","",IFERROR(VLOOKUP($D25,'Products & Pricing'!$A$14:$D$28,4,FALSE),"")) | G25: =IF($D25="","",N(E25)*N(F25)) | J25: =IF($D25="","",N(G25)+N(H25)-N(I25)) | L25: =IF($D25="","",N(J25)-N(K25))
... F313: =IF($D313="","",IFERROR(VLOOKUP($D313,'Products & Pricing'!$A$14:$D$28,4,FALSE),"")) | G313: =IF($D313="","",N(E313)*N(F313)) | J313: =IF($D313="","",N(G313)+N(H313)-N(I313)) | L313: =IF($D313="","",N(J313)-N(K313))
C314: TOTALS | E314: =SUM(E14:E313) | G314: =SUM(G14:G313) | H314: =SUM(H14:H313) | I314: =SUM(I14:I313) | J314: =SUM(J14:J313) | K314: =SUM(K14:K313) | L314: =SUM(L14:L313)

Sheet Orders
A1: Orders — Who Ordered What & Has It Shipped
A2: Your fulfillment command center: customer, items, shipping address, tracking, and order status.
A4: WHAT THIS TAB IS FOR: making sure nobody who paid you gets forgotten. One row per order (money details live on the Sales Log).
A5: WHAT GOES HERE: the same Order # you used on the Sales Log, the date it came in, customer name and contact,
A6: what they ordered (dropdown — or type a list like '2x Drifters, 1x The Classics' for multi-item orders), quantity,
A7: and the FULL shipping address (street / city / state / ZIP).
A8: AS YOU WORK THE ORDER: update Status — New → In Production → Packed → Shipped → Delivered.
A9: When it ships, enter Date Shipped and the Tracking #, and flip Fulfilled? to Yes (turns green; No stays red so
A10: unshipped orders jump out at you). The counters below always show how many orders are still waiting on you.
A11: KICKSTARTER BACKER REWARDS count as orders too — enter them here the day the campaign ends.
B13: Orders received: | C13: =COUNTA(A15:A314) | D13: Fulfilled: | E13: =COUNTIF(O15:O314,"Yes") | G13: Still open: | H13: =C13-E13 | J13: % fulfilled: | K13: =IF(C13=0,"",E13/C13)
A14: Order # | B14: Date Received | C14: Customer Name | D14: Email / Phone | E14: Product(s) Ordered | F14: Qty | G14: Street Address | H14: City | I14: State | J14: ZIP | K14: Ship Method | L14: Date Shipped | M14: Tracking # | N14: Status | O14: Fulfilled? | P14: Notes

Sheet Monthly Cash Flow
A1: Monthly Cash Flow — Money In vs. Money Out, Month by Month
A2: Fully automatic. Shows whether each month put you ahead (green) or behind (red), and your running cash balance.
A4: WHAT THIS TAB IS FOR: seeing your cash trend. Every number here is pulled automatically from the DATES you enter
A5: on Funding, Sales Log, Capital, and Operating Costs — you never type in the table itself.
A6: THE ONLY TWO THINGS YOU CAN EDIT: (1) Starting Cash below — money you already had before Month 1;
A7: (2) the Month column — if Year 1 doesn't start in January, change the first month and the rest follow.
A8: HOW TO READ IT: 'Net This Month' green = you made more than you spent that month. 'Running Cash Balance' red =
A9: you have less than $0 overall — time to slow spending or raise more funding.
A11: Starting Cash: | B11: 0
A13: Month | B13: Money In: Funding | C13: Money In: Sales | D13: TOTAL IN | E13: Money Out: Capital | F13: Money Out: Operating | G13: TOTAL OUT | H13: NET THIS MONTH | I13: RUNNING CASH BALANCE
A14: 46023 | B14: =SUMIFS(Funding!$G$14:$G$313,Funding!$A$14:$A$313,">="&$A14,Funding!$A$14:$A$313,"<"&EDATE($A14,1)) | C14: =SUMIFS('Sales Log'!$L$14:$L$313,'Sales Log'!$A$14:$A$313,">="&$A14,'Sales Log'!$A$14:$A$313,"<"&EDATE($A14,1)) | D14: =B14+C14 | E14: =SUMIFS(Capital!$G$14:$G$63,Capital!$E$14:$E$63,">="&$A14,Capital!$E$14:$E$63,"<"&EDATE($A14,1)) | F14: =SUMIFS('Operating Costs'!$E$13:$E$212,'Operating Costs'!$A$13:$A$212,">="&$A14,'Operating Costs'!$A$13:$A$212,"<"&EDATE($A14,1)) | G14: =E14+F14 | H14: =D14-G14 | I14: =$B$11+H14
A15: =EDATE(A14,1) | B15: =SUMIFS(Funding!$G$14:$G$313,Funding!$A$14:$A$313,">="&$A15,Funding!$A$14:$A$313,"<"&EDATE($A15,1)) | C15: =SUMIFS('Sales Log'!$L$14:$L$313,'Sales Log'!$A$14:$A$313,">="&$A15,'Sales Log'!$A$14:$A$313,"<"&EDATE($A15,1)) | D15: =B15+C15 | E15: =SUMIFS(Capital!$G$14:$G$63,Capital!$E$14:$E$63,">="&$A15,Capital!$E$14:$E$63,"<"&EDATE($A15,1)) | F15: =SUMIFS('Operating Costs'!$E$13:$E$212,'Operating Costs'!$A$13:$A$212,">="&$A15,'Operating Costs'!$A$13:$A$212,"<"&EDATE($A15,1)) | G15: =E15+F15 | H15: =D15-G15 | I15: =I14+H15
A16: =EDATE(A15,1) | B16: =SUMIFS(Funding!$G$14:$G$313,Funding!$A$14:$A$313,">="&$A16,Funding!$A$14:$A$313,"<"&EDATE($A16,1)) | C16: =SUMIFS('Sales Log'!$L$14:$L$313,'Sales Log'!$A$14:$A$313,">="&$A16,'Sales Log'!$A$14:$A$313,"<"&EDATE($A16,1)) | D16: =B16+C16 | E16: =SUMIFS(Capital!$G$14:$G$63,Capital!$E$14:$E$63,">="&$A16,Capital!$E$14:$E$63,"<"&EDATE($A16,1)) | F16: =SUMIFS('Operating Costs'!$E$13:$E$212,'Operating Costs'!$A$13:$A$212,">="&$A16,'Operating Costs'!$A$13:$A$212,"<"&EDATE($A16,1)) | G16: =E16+F16 | H16: =D16-G16 | I16: =I15+H16
A17: =EDATE(A16,1) | B17: =SUMIFS(Funding!$G$14:$G$313,Funding!$A$14:$A$313,">="&$A17,Funding!$A$14:$A$313,"<"&EDATE($A17,1)) | C17: =SUMIFS('Sales Log'!$L$14:$L$313,'Sales Log'!$A$14:$A$313,">="&$A17,'Sales Log'!$A$14:$A$313,"<"&EDATE($A17,1)) | D17: =B17+C17 | E17: =SUMIFS(Capital!$G$14:$G$63,Capital!$E$14:$E$63,">="&$A17,Capital!$E$14:$E$63,"<"&EDATE($A17,1)) | F17: =SUMIFS('Operating Costs'!$E$13:$E$212,'Operating Costs'!$A$13:$A$212,">="&$A17,'Operating Costs'!$A$13:$A$212,"<"&EDATE($A17,1)) | G17: =E17+F17 | H17: =D17-G17 | I17: =I16+H17
A18: =EDATE(A17,1) | B18: =SUMIFS(Funding!$G$14:$G$313,Funding!$A$14:$A$313,">="&$A18,Funding!$A$14:$A$313,"<"&EDATE($A18,1)) | C18: =SUMIFS('Sales Log'!$L$14:$L$313,'Sales Log'!$A$14:$A$313,">="&$A18,'Sales Log'!$A$14:$A$313,"<"&EDATE($A18,1)) | D18: =B18+C18 | E18: =SUMIFS(Capital!$G$14:$G$63,Capital!$E$14:$E$63,">="&$A18,Capital!$E$14:$E$63,"<"&EDATE($A18,1)) | F18: =SUMIFS('Operating Costs'!$E$13:$E$212,'Operating Costs'!$A$13:$A$212,">="&$A18,'Operating Costs'!$A$13:$A$212,"<"&EDATE($A18,1)) | G18: =E18+F18 | H18: =D18-G18 | I18: =I17+H18
A19: =EDATE(A18,1) | B19: =SUMIFS(Funding!$G$14:$G$313,Funding!$A$14:$A$313,">="&$A19,Funding!$A$14:$A$313,"<"&EDATE($A19,1)) | C19: =SUMIFS('Sales Log'!$L$14:$L$313,'Sales Log'!$A$14:$A$313,">="&$A19,'Sales Log'!$A$14:$A$313,"<"&EDATE($A19,1)) | D19: =B19+C19 | E19: =SUMIFS(Capital!$G$14:$G$63,Capital!$E$14:$E$63,">="&$A19,Capital!$E$14:$E$63,"<"&EDATE($A19,1)) | F19: =SUMIFS('Operating Costs'!$E$13:$E$212,'Operating Costs'!$A$13:$A$212,">="&$A19,'Operating Costs'!$A$13:$A$212,"<"&EDATE($A19,1)) | G19: =E19+F19 | H19: =D19-G19 | I19: =I18+H19
A20: =EDATE(A19,1) | B20: =SUMIFS(Funding!$G$14:$G$313,Funding!$A$14:$A$313,">="&$A20,Funding!$A$14:$A$313,"<"&EDATE($A20,1)) | C20: =SUMIFS('Sales Log'!$L$14:$L$313,'Sales Log'!$A$14:$A$313,">="&$A20,'Sales Log'!$A$14:$A$313,"<"&EDATE($A20,1)) | D20: =B20+C20 | E20: =SUMIFS(Capital!$G$14:$G$63,Capital!$E$14:$E$63,">="&$A20,Capital!$E$14:$E$63,"<"&EDATE($A20,1)) | F20: =SUMIFS('Operating Costs'!$E$13:$E$212,'Operating Costs'!$A$13:$A$212,">="&$A20,'Operating Costs'!$A$13:$A$212,"<"&EDATE($A20,1)) | G20: =E20+F20 | H20: =D20-G20 | I20: =I19+H20
A21: =EDATE(A20,1) | B21: =SUMIFS(Funding!$G$14:$G$313,Funding!$A$14:$A$313,">="&$A21,Funding!$A$14:$A$313,"<"&EDATE($A21,1)) | C21: =SUMIFS('Sales Log'!$L$14:$L$313,'Sales Log'!$A$14:$A$313,">="&$A21,'Sales Log'!$A$14:$A$313,"<"&EDATE($A21,1)) | D21: =B21+C21 | E21: =SUMIFS(Capital!$G$14:$G$63,Capital!$E$14:$E$63,">="&$A21,Capital!$E$14:$E$63,"<"&EDATE($A21,1)) | F21: =SUMIFS('Operating Costs'!$E$13:$E$212,'Operating Costs'!$A$13:$A$212,">="&$A21,'Operating Costs'!$A$13:$A$212,"<"&EDATE($A21,1)) | G21: =E21+F21 | H21: =D21-G21 | I21: =I20+H21
A22: =EDATE(A21,1) | B22: =SUMIFS(Funding!$G$14:$G$313,Funding!$A$14:$A$313,">="&$A22,Funding!$A$14:$A$313,"<"&EDATE($A22,1)) | C22: =SUMIFS('Sales Log'!$L$14:$L$313,'Sales Log'!$A$14:$A$313,">="&$A22,'Sales Log'!$A$14:$A$313,"<"&EDATE($A22,1)) | D22: =B22+C22 | E22: =SUMIFS(Capital!$G$14:$G$63,Capital!$E$14:$E$63,">="&$A22,Capital!$E$14:$E$63,"<"&EDATE($A22,1)) | F22: =SUMIFS('Operating Costs'!$E$13:$E$212,'Operating Costs'!$A$13:$A$212,">="&$A22,'Operating Costs'!$A$13:$A$212,"<"&EDATE($A22,1)) | G22: =E22+F22 | H22: =D22-G22 | I22: =I21+H22
A23: =EDATE(A22,1) | B23: =SUMIFS(Funding!$G$14:$G$313,Funding!$A$14:$A$313,">="&$A23,Funding!$A$14:$A$313,"<"&EDATE($A23,1)) | C23: =SUMIFS('Sales Log'!$L$14:$L$313,'Sales Log'!$A$14:$A$313,">="&$A23,'Sales Log'!$A$14:$A$313,"<"&EDATE($A23,1)) | D23: =B23+C23 | E23: =SUMIFS(Capital!$G$14:$G$63,Capital!$E$14:$E$63,">="&$A23,Capital!$E$14:$E$63,"<"&EDATE($A23,1)) | F23: =SUMIFS('Operating Costs'!$E$13:$E$212,'Operating Costs'!$A$13:$A$212,">="&$A23,'Operating Costs'!$A$13:$A$212,"<"&EDATE($A23,1)) | G23: =E23+F23 | H23: =D23-G23 | I23: =I22+H23
A24: =EDATE(A23,1) | B24: =SUMIFS(Funding!$G$14:$G$313,Funding!$A$14:$A$313,">="&$A24,Funding!$A$14:$A$313,"<"&EDATE($A24,1)) | C24: =SUMIFS('Sales Log'!$L$14:$L$313,'Sales Log'!$A$14:$A$313,">="&$A24,'Sales Log'!$A$14:$A$313,"<"&EDATE($A24,1)) | D24: =B24+C24 | E24: =SUMIFS(Capital!$G$14:$G$63,Capital!$E$14:$E$63,">="&$A24,Capital!$E$14:$E$63,"<"&EDATE($A24,1)) | F24: =SUMIFS('Operating Costs'!$E$13:$E$212,'Operating Costs'!$A$13:$A$212,">="&$A24,'Operating Costs'!$A$13:$A$212,"<"&EDATE($A24,1)) | G24: =E24+F24 | H24: =D24-G24 | I24: =I23+H24
A25: =EDATE(A24,1) | B25: =SUMIFS(Funding!$G$14:$G$313,Funding!$A$14:$A$313,">="&$A25,Funding!$A$14:$A$313,"<"&EDATE($A25,1)) | C25: =SUMIFS('Sales Log'!$L$14:$L$313,'Sales Log'!$A$14:$A$313,">="&$A25,'Sales Log'!$A$14:$A$313,"<"&EDATE($A25,1)) | D25: =B25+C25 | E25: =SUMIFS(Capital!$G$14:$G$63,Capital!$E$14:$E$63,">="&$A25,Capital!$E$14:$E$63,"<"&EDATE($A25,1)) | F25: =SUMIFS('Operating Costs'!$E$13:$E$212,'Operating Costs'!$A$13:$A$212,">="&$A25,'Operating Costs'!$A$13:$A$212,"<"&EDATE($A25,1)) | G25: =E25+F25 | H25: =D25-G25 | I25: =I24+H25
A26: YEAR 1 | B26: =SUM(B14:B25) | C26: =SUM(C14:C25) | D26: =SUM(D14:D25) | E26: =SUM(E14:E25) | F26: =SUM(F14:F25) | G26: =SUM(G14:G25) | H26: =SUM(H14:H25) | I26: =I25
